LICENSE
MANIFEST.in
README.rst
requirements.txt
setup.cfg
setup.py
draceditor/__init__.py
draceditor/admin.py
draceditor/api.py
draceditor/fields.py
draceditor/models.py
draceditor/settings.py
draceditor/urls.py
draceditor/utils.py
draceditor/views.py
draceditor/widgets.py
draceditor.egg-info/PKG-INFO
draceditor.egg-info/SOURCES.txt
draceditor.egg-info/dependency_links.txt
draceditor.egg-info/not-zip-safe
draceditor.egg-info/requires.txt
draceditor.egg-info/top_level.txt
draceditor/extensions/__init__.py
draceditor/extensions/del_ins.py
draceditor/extensions/emoji.py
draceditor/extensions/mention.py
draceditor/extensions/urlize.py
draceditor/static/draceditor/css/draceditor.css
draceditor/static/draceditor/js/draceditor-backup.js
draceditor/static/draceditor/js/draceditor.js
draceditor/static/plugins/css/ace.min.css
draceditor/static/plugins/css/semantic.min.css
draceditor/static/plugins/fonts/icons.eot
draceditor/static/plugins/fonts/icons.otf
draceditor/static/plugins/fonts/icons.svg
draceditor/static/plugins/fonts/icons.ttf
draceditor/static/plugins/fonts/icons.woff
draceditor/static/plugins/fonts/icons.woff2
draceditor/static/plugins/images/commonmark.png
draceditor/static/plugins/images/flags.png
draceditor/static/plugins/images/smile.png
draceditor/static/plugins/js/ace.js
draceditor/static/plugins/js/emojis.min.js
draceditor/static/plugins/js/ext-language_tools.js
draceditor/static/plugins/js/highlight.min.js
draceditor/static/plugins/js/jquery.min.js
draceditor/static/plugins/js/mode-markdown.js
draceditor/static/plugins/js/semantic.min.js
draceditor/static/plugins/js/theme-github.js
draceditor/static/plugins/js/snippets/markdown.js
draceditor/templates/draceditor/editor.html
draceditor/templates/draceditor/emoji.html
draceditor/templates/draceditor/guide.html
draceditor/templates/draceditor/toolbar.html
draceditor/templatetags/__init__.py
draceditor/templatetags/dractags.py