Metadata-Version: 1.1
Name: draceditor
Version: 1.1.8
Summary: Django Markdown Editor built for Dracos Linux https://dracos-linux.org
Home-page: https://github.com/agusmakmun/dracos-markdown-editor
Author: Agus Makmun (Summon Agus)
Author-email: agus@python.web.id
License: GNUGPL-v3
Download-URL: https://github.com/agusmakmun/djipsum/tarball/v1.1.8
Keywords: draceditor,django markdown,django markdown editor
Platform: UNKNOWN
Classifier: Development Status :: 5 - Production/Stable
Classifier: Environment :: Web Environment
Classifier: Framework :: Django
Classifier: Framework :: Django :: 1.8
Classifier: Framework :: Django :: 1.9
Classifier: Framework :: Django :: 1.10
Classifier: Intended Audience :: Developers
Classifier: Operating System :: OS Independent
Classifier: Programming Language :: JavaScript
Classifier: Programming Language :: Python
Classifier: Programming Language :: Python :: 2.7
Classifier: Programming Language :: Python :: 3.3
Classifier: Programming Language :: Python :: 3.5
Classifier: Topic :: Software Development :: Libraries :: Python Modules
Classifier: License :: OSI Approved :: GNU General Public License v3 (GPLv3)
